{
	"uid" : "1337b0101",
	"data" : {
		"avatar" : "https://ca.slack-edge.com/TDB9SC82D-UU2QY4JQ4-94d00cf9ed59-48",
		"fullname" : "Yassine Mellouki",
		"firstname" : "Yassine",
		"lastname" : "Mellouki",
		"details" : [
	        {
	          "label":"Job",
	          "value":"Full Stack Web/Mobile JS Developer"
	        },
	        {
	          "label":"Technologies",
	          "value": ["JS/ES6", "ReactJS", "ReactNatie", "NodeJS/ExpressJS", "MongoDB", "VIM", "..." ]
	        },
	        {
	          "label":"Country",
	          "value":"Morocco"
	        },
	        {
	          "label":"email",
	          "value":"yassinemellouki4@gmail.com"
	        },
	        {
	          "label":"phone",
	          "value":"+212671815573"
	        },
          {
            "label": "address",
            "value": "343, Marrakech, Morocco"
          }
		]
	},
	"token" : "Anxbc94d52sMpdi-MhFgjJ75qLApxbc9vp-DMskd"
}
